httpwrapper/__init__.py
httpwrapper/async_client.py
httpwrapper/cache.py
httpwrapper/circuit_breaker.py
httpwrapper/client.py
httpwrapper/config.py
httpwrapper/exceptions.py
httpwrapper/metrics_collector.py
httpwrapper/plugin_system.py
httpwrapper/retry_manager.py
httpwrapper-0.1.1.dist-info/licenses/LICENSE
httpwrapper-0.1.1.dist-info/METADATA
httpwrapper-0.1.1.dist-info/WHEEL
httpwrapper-0.1.1.dist-info/top_level.txt
httpwrapper-0.1.1.dist-info/RECORD
